py_code_timing.py
py_code_timing-1.0.1.dist-info/LICENSE
py_code_timing-1.0.1.dist-info/METADATA
py_code_timing-1.0.1.dist-info/WHEEL
py_code_timing-1.0.1.dist-info/top_level.txt
py_code_timing-1.0.1.dist-info/RECORD
