Metadata-Version: 2.1
Name: py-code-timing
Version: 1.0.1
Summary: Python code timing utilities
Author-email: Purple Elephant <purple.elephant1037@gmail.com>
Project-URL: Homepage, https://github.com/purple-elephant1037/py_code_timing
Project-URL: Test code, https://github.com/purple-elephant1037/py_code_timing/tree/master/tests
Classifier: Programming Language :: Python :: 3
Classifier: License :: OSI Approved :: MIT License
Classifier: Operating System :: OS Independent
Classifier: Topic :: Utilities
Requires-Python: >=3.7
License-File: LICENSE
